UIAnalyzer/Driver.py
UIAnalyzer/PageCognition.py
UIAnalyzer/Rect.py
UIAnalyzer/Utils.py
UIAnalyzer/XML.py
UIAnalyzer/__init__.py
UIAnalyzer/Assets/Arial.ttf
UIAnalyzer/Example/__init__.py
UIAnalyzer/Example/example.py
UIAnalyzer-0.3.1.dist-info/LICENSE
UIAnalyzer-0.3.1.dist-info/METADATA
UIAnalyzer-0.3.1.dist-info/WHEEL
UIAnalyzer-0.3.1.dist-info/top_level.txt
UIAnalyzer-0.3.1.dist-info/RECORD
